C4_files/output_comb.sv
/////////////////////////////////////////////////////////////////////
// Design unit: output_comb
//            :
// File name  : output_comb.sv
//            :
// Description: Output Register code for C4 Lab exercise
//            :
// Limitations: None
//            : 
// System     : SystemVerilog IEEE 1800-2005
//            :
// Author     : Mark Zwolinski
//            : School of Electronics and Computer Science
//            : University of Southampton
//            : Southampton SO17 1BJ, UK
//            : mz@ecs.soton.ac.uk
//
// Revision   : Version 1.0 28/10/25
//
/////////////////////////////////////////////////////////////////////

module output_comb (output logic k, l, input logic s, t, s_bar, t_bar, b);

logic b_bar, v, w;

nand g7 (v, s_bar, t);
nand g8 (w, t_bar, b);
nand g9 (k, v, w);
not g10 (b_bar, b);
and g11 (l, b_bar, t);
    
endmodule

C4_files/d_ff.sv
/////////////////////////////////////////////////////////////////////
// Design unit: d_ff
//            :
// File name  : d_ff.sv
//            :
// Description: D Flip-flop code for C4 Lab exercise
//            :
// Limitations: None
//            : 
// System     : SystemVerilog IEEE 1800-2005
//            :
// Author     : Mark Zwolinski
//            : School of Electronics and Computer Science
//            : University of Southampton
//            : Southampton SO17 1BJ, UK
//            : mz@ecs.soton.ac.uk
//
// Revision   : Version 1.0 28/08/17
//            : Version 2.0 04/11/20 
//
/////////////////////////////////////////////////////////////////////


// Storage element
// D ff with async rset storing 1 bit of state



module d_ff (output logic q, qbar, input logic clk, rst, d);

always_ff @(posedge clk, negedge rst) // falling adge on clk or asynchronous reset
  if (~rst) // active low reset
    begin
    q <= 1'b0;
    qbar <= 1'b1;
    end // normal operation 
  else
    begin
    q <= d;// stores the value of d (state)
    qbar <= ~d; // inverted state logic
    end

endmodule

// q is the state bit

C4_files/next_state.sv
/////////////////////////////////////////////////////////////////////
// Design unit: next_state
//            :
// File name  : next_state.sv
//            :
// Description: Next state logic code for C4 Lab exercise
//            :
// Limitations: None
//            : 
// System     : SystemVerilog IEEE 1800-2005
//            :
// Author     : Mark Zwolinski
//            : School of Electronics and Computer Science
//            : University of Southampton
//            : Southampton SO17 1BJ, UK
//            : mz@ecs.soton.ac.uk
//
// Revision   : Version 1.0 28/08/17
//            : Version 2.0 04/11/20 Use `define and `ifdef
//
/////////////////////////////////////////////////////////////////////


// macros are preprocessor directives handled before simulation/compilation
// FSM brain




// To insert a fault, change ONE of the following lines to `define`

`undef FSA0 // undefine a macro 
`define FSA1 // defined it for 2.3 b

// by default no fault is active

module next_state (output logic s_plus, t_plus, input logic s, s_bar, t, t_bar, a);

// s, t --> current state
// a --> input. s_plus, t_plus --> next state


logic a_bar, e, f, g, h; // internal signals

nand g0 (s_plus, e, f); // a nand gate with input from (outputs of nand g1 and nand g2) the output = s+

// S+ = NAND ( NAND (s_bar,t), NAND (s,a,t_bar)) or NAND G1, G2


nand g1 (e, s_bar, t); // nand gate with input s_bar and t and output e



// The operation of `ifdef means that if the preprocessor evaluates these before compilation/synthesis. If the macro named in 
// `ifdef is defined then the code b/w tht `ifdeff and the next preprocessing directive ins kept otherwise its skipped.


`ifdef FSA0 // include following block if MACRO is not defined ****
assign f = 1'b0; // if FSA0 is defined only then f --> 0  *** Basically stuck at 0 fault
`elsif FSA1 // else if for preprocessor
assign f = 1'b1;
`else
nand g2 (f, s, a, t_bar); // nand gate with input s,a,t and output f
`endif

nand g3 (t_plus, g, h); // T+ = NAND(g4), NAND(g5)
nand g4 (g, a, s_bar, t_bar);
nand g5 (h, a_bar, s_bar, t);
not g6 (a_bar, a);

endmodule

C4_files/c4.sv
/////////////////////////////////////////////////////////////////////
// Design unit: c4
//            :
// File name  : c4.sv
//            :
// Description: Top level code for C4 Lab exercise
//            :
// Limitations: None
//            : 
// System     : SystemVerilog IEEE 1800-2005
//            :
// Author     : Mark Zwolinski
//            : School of Electronics and Computer Science
//            : University of Southampton
//            : Southampton SO17 1BJ, UK
//            : mz@ecs.soton.ac.uk
//
// Revision   : Version 1.0 28/08/17
//            : Version 2.0 04/11/20 
//
/////////////////////////////////////////////////////////////////////


module c4 (output logic k, l, input logic n_clk, rst, a);

logic s_plus, t_plus, s_bar, t_bar, clk,s,t;

assign clk = ~n_clk; // clock inversion

next_state n0 (.*); // instanties everything from next_state.sv
d_ff d0 (.q(s), .qbar(s_bar), .clk(clk), .rst(rst), .d(s_plus)); // stores the states S and T 
d_ff d1 (.q(t), .qbar(t_bar), .clk(clk), .rst(rst), .d(t_plus));
//output_reg o1 (.*);
output_comb c1 (.*)




// Data flow:     (S, T) → next_state → (S+, T+) → flip-flops → (S, T)

endmodule

C4_files/test_c4.sv
/////////////////////////////////////////////////////////////////////
// Design unit: test_c4
//            :
// File name  : test_c4.sv
//            :
// Description: Testbench for for C4 Lab exercise
//            :
// Limitations: None
//            : 
// System     : SystemVerilog IEEE 1800-2005
//            :
// Author     : Mark Zwolinski
//            : School of Electronics and Computer Science
//            : University of Southampton
//            : Southampton SO17 1BJ, UK
//            : mz@ecs.soton.ac.uk
//
// Revision   : Version 1.0 28/08/17
//            : Version 2.0 04/11/20 
//
/////////////////////////////////////////////////////////////////////


module test_c4;

timeunit 1ns;
timeprecision 100ps;

logic s, t;
logic n_clk, rst, a;

c4 c4 (.*);

initial 
  begin
  n_clk = 0;
  #20;
  forever #10 n_clk = ~n_clk; // the internal clock is inverted to suit FPGA
  end
  
initial

  begin
  rst = 1;
  a = 0;
  #10 rst = 0;
  #10 rst = 1;
  #20 a = 0;
  #20 a = 1;
  #20 a = 1;
  #20 a = 1;
  #20 a = 0;
  #20 a = 1;
  #20 a = 0;
  #20 a = 1;
  #20 a = 1;
  #20 a = 0;
  #20 a = 0;
  #20 $finish;
  end

endmodule

C4_files/c4_300ns.vcd
$date
	Thu Apr 30 21:24:45 2026
$end
$version
	Icarus Verilog
$end
$timescale
	100ps
$end
$scope module test_c4 $end
$var wire 1 ! t $end
$var wire 1 " s $end
$var reg 1 # a $end
$var reg 1 $ n_clk $end
$var reg 1 % rst $end
$scope module c4 $end
$var wire 1 # a $end
$var wire 1 & clk $end
$var wire 1 $ n_clk $end
$var wire 1 % rst $end
$var wire 1 ' t_plus $end
$var wire 1 ( t_bar $end
$var wire 1 ! t $end
$var wire 1 ) s_plus $end
$var wire 1 * s_bar $end
$var wire 1 " s $end
$scope module d0 $end
$var wire 1 & clk $end
$var wire 1 % rst $end
$var wire 1 ) d $end
$var reg 1 " q $end
$var reg 1 * qbar $end
$upscope $end
$scope module d1 $end
$var wire 1 & clk $end
$var wire 1 % rst $end
$var wire 1 ' d $end
$var reg 1 ! q $end
$var reg 1 ( qbar $end
$upscope $end
$scope module n0 $end
$var wire 1 # a $end
$var wire 1 + a_bar $end
$var wire 1 , e $end
$var wire 1 - f $end
$var wire 1 . g $end
$var wire 1 / h $end
$var wire 1 " s $end
$var wire 1 * s_bar $end
$var wire 1 ) s_plus $end
$var wire 1 ! t $end
$var wire 1 ( t_bar $end
$var wire 1 ' t_plus $end
$upscope $end
$upscope $end
$upscope $end
$enddefinitions $end
$comment Show the parameter values. $end
$dumpall
$end
#0
$dumpvars
x/
1.
1-
x,
1+
x*
x)
x(
x'
1&
1%
0$
0#
x"
x!
$end
#100
0)
0'
1,
1/
1(
0!
1*
0"
0%
#200
1%
#300
0&
1$
#400
1&
0$
#500
0&
1$
#600
1)
0,
0(
1!
0'
1&
1.
0+
0$
1#
#700
0&
1$
#800
0-
1,
0*
1"
1(
0!
1&
0$
#900
0&
1$
#1000
1&
0$
#1100
0&
1$
#1200
1*
0"
0)
1&
1-
1+
0$
0#
#1300
0&
1$
#1400
1)
0,
0(
1!
0'
1&
1.
0+
0$
1#
#1500
0&
1$
#1600
0)
1,
0*
1"
1(
0!
0'
1/
1&
1+
0$
0#
#1700
0&
1$
#1800
1)
1&
0-
0+
0$
1#
#1900
0&
1$
#2000
1&
0$
#2100
0&
1$
#2200
1*
0"
0)
1&
1-
1+
0$
0#
